irrigation30/__init__.py
irrigation30/irrigation30.py
irrigation30/irrigation30_angela.py
irrigation30-0.0.2.dist-info/LICENSE
irrigation30-0.0.2.dist-info/METADATA
irrigation30-0.0.2.dist-info/WHEEL
irrigation30-0.0.2.dist-info/top_level.txt
irrigation30-0.0.2.dist-info/RECORD
